podsearch_sp/__init__.py
podsearch_sp-0.1.0.dist-info/WHEEL
podsearch_sp-0.1.0.dist-info/METADATA
podsearch_sp-0.1.0.dist-info/RECORD
