Metadata-Version: 2.1
Name: podsearch_sp
Version: 0.1.0
Summary: Let's test some code!
Author-email: Seb <sebastianpikand@gmail.com>
Classifier: License :: OSI Approved :: MIT License
Project-URL: Home, https://github.com/sebastianpikand
